{ "type": "success", "value": [ { "id": 17, "joke": "Chuck Norris does not teabag the ladies. He potato-sacks them.", "categories": ["explicit"] }, { "id": 121, "joke": "It takes 14 puppeteers to make Chuck Norris smile, but only 2 to make him destroy an orphanage.", "categories": [] }, { "id": 480, "joke": "The class object inherits from Chuck Norris", "categories": ["nerdy"] }, { "id": 203, "joke": "Chuck Norris can lead a horse to water AND make it drink.", "categories": [] }, { "id": 546, "joke": "Chuck Norris does infinit loops in 4 seconds.", "categories": ["nerdy"] }, { "id": 411, "joke": "The pen is mighter than the sword, but only if the pen is held by Chuck Norris.", "categories": [] }, { "id": 305, "joke": "Chuck Norris knows everything there is to know - Except for the definition of mercy.", "categories": [] }, { "id": 216, "joke": "Since 1940, the year Chuck Norris was born, roundhouse-kick related deaths have increased 13,000 percent.", "categories": [] } ] }